MANIFEST.in
README.md
setup.py
terralego/__init__.py
terralego/conf.py
terralego/geocoding.py
terralego/geodirectory.py
terralego/utils.py
terralego.egg-info/PKG-INFO
terralego.egg-info/SOURCES.txt
terralego.egg-info/dependency_links.txt
terralego.egg-info/not-zip-safe
terralego.egg-info/requires.txt
terralego.egg-info/top_level.txt