Metadata-Version: 1.1
Name: terralego
Version: 0.1
Summary: Python bindings for Terralego services.
Home-page: https://terralego.fr
Author: Autonomens
Author-email: contact@autonomens.fr
License: MIT
Platform: UNKNOWN
Classifier: Development Status :: 3 - Alpha
Classifier: License :: OSI Approved :: MIT License
Classifier: Programming Language :: Python :: 3
